lk_heuristic/__init__.py
lk_heuristic/models/__init__.py
lk_heuristic/models/edge.py
lk_heuristic/models/node.py
lk_heuristic/models/tour.py
lk_heuristic/models/tsp.py
lk_heuristic/plots/__init__.py
lk_heuristic/samples/__init__.py
lk_heuristic/samples/a280.tsp
lk_heuristic/samples/att48.tsp
lk_heuristic/samples/hexagon_2d.tsp
lk_heuristic/samples/hexagon_3d.tsp
lk_heuristic/solutions/__init__.py
lk_heuristic/utils/__init__.py
lk_heuristic/utils/cost_funcs.py
lk_heuristic/utils/io_funcs.py
lk_heuristic/utils/plot_funcs.py
lk_heuristic/utils/solver_funcs.py
lk_heuristic/utils/timer_funcs.py
lk_heuristic-0.0.4.dist-info/LICENSE
lk_heuristic-0.0.4.dist-info/METADATA
lk_heuristic-0.0.4.dist-info/WHEEL
lk_heuristic-0.0.4.dist-info/top_level.txt
lk_heuristic-0.0.4.dist-info/RECORD
