Metadata-Version: 2.1
Name: lk-heuristic
Version: 0.0.4
Summary: Lin-Kernighan Heuristic in Python
Home-page: https://github.com/kikocastroneto/lk_heuristic
Author: Frederico de Castro Neto
Author-email: fred.cneto@hotmail.com
License: MIT
Keywords: tsp,lk,lkh
Classifier: Programming Language :: Python :: 3
Classifier: License :: OSI Approved :: MIT License
Classifier: Operating System :: OS Independent
Requires-Python: >=3.7
License-File: LICENSE
Requires-Dist: plotly ==5.5.0
